{"nodes": [{"attr": "rigidness", "rvname": "set_d", "focus": true, "subtype": "frame", "weights": [0.025708936986216652, 0.97429106301378343, 0.0], "type": "rv", "id": "[rigidness] set_d"}, {"specific": "emb", "subtype": "seed", "type": "fac", "id": "seed0", "weights": [0.47642867599200001, 0.52357132400799999, 0.0]}, {"subtype": "verb_sim", "type": "fac", "id": "verb_sim1"}, {"attr": "rigidness", "rvname": "made_d", "subtype": "frame", "weights": [0.017079251265302908, 0.98292074873469704, 0.0], "type": "rv", "id": "[rigidness] made_d"}, {"subtype": "verb_sim", "type": "fac", "id": "verb_sim2"}, {"attr": "rigidness", "rvname": "turned_d", "subtype": "frame", "weights": [8.5997829881452088e-05, 0.99991400217011861, 0.0], "type": "rv", "id": "[rigidness] turned_d"}, {"subtype": "verb_sim", "type": "fac", "id": "verb_sim3"}, {"attr": "rigidness", "rvname": "opened_d", "subtype": "frame", "weights": [0.0086170277190036233, 0.99138297228099637, 0.0], "type": "rv", "id": "[rigidness] opened_d"}], "stats": {"rvs": {"frame": 4}, "facs": {"seed": 1, "verb_sim": 3}, "n_facs": 4, "focus": "set_d", "n_rvs": 4}, "links": [{"source": "seed0", "type": "seed", "target": "[rigidness] set_d", "weights": [0.47642867599200001, 0.52357132400799999, 0.0]}, {"source": "verb_sim1", "type": "verb_sim", "target": "[rigidness] made_d", "weights": [0.26338720285721112, 0.73661279714278893, 0.0]}, {"source": "verb_sim1", "type": "verb_sim", "target": "[rigidness] set_d", "weights": [0.24796851844953921, 0.75203148155046085, 0.0]}, {"source": "verb_sim2", "type": "verb_sim", "target": "[rigidness] turned_d", "weights": [0.26916067227759854, 0.73083932772240134, 0.0]}, {"source": "verb_sim2", "type": "verb_sim", "target": "[rigidness] set_d", "weights": [0.22235192881418026, 0.77764807118581969, 0.0]}, {"source": "verb_sim3", "type": "verb_sim", "target": "[rigidness] opened_d", "weights": [0.26611791149916725, 0.73388208850083281, 0.0]}, {"source": "verb_sim3", "type": "verb_sim", "target": "[rigidness] set_d", "weights": [0.23522716940531288, 0.76477283059468715, 0.0]}]}
