{"nodes": [{"attr": "rigidness", "rvname": "took_dp_of", "focus": true, "subtype": "frame", "weights": [5.1334095947245322e-06, 0.99999486659040537, 0.0], "type": "rv", "id": "[rigidness] took_dp_of"}, {"specific": "emb", "subtype": "seed", "type": "fac", "id": "seed0", "weights": [0.259935827422, 0.74006417257799995, 0.0]}, {"specific": "hard", "subtype": "seed", "type": "fac", "id": "seed1", "weights": [0.20000000000000001, 0.69999999999999996, 0.10000000000000001]}, {"subtype": "verb_sim", "type": "fac", "id": "verb_sim2"}, {"attr": "rigidness", "rvname": "made_dp_in", "subtype": "frame", "weights": [1.5129625310066222e-06, 0.99999848703746907, 0.0], "type": "rv", "id": "[rigidness] made_dp_in"}, {"subtype": "verb_sim", "type": "fac", "id": "verb_sim3"}, {"attr": "rigidness", "rvname": "made_dp_on", "subtype": "frame", "weights": [5.7319693294815189e-08, 0.99999994268030667, 0.0], "type": "rv", "id": "[rigidness] made_dp_on"}, {"subtype": "verb_sim", "type": "fac", "id": "verb_sim4"}, {"attr": "rigidness", "rvname": "held_dp_for", "subtype": "frame", "weights": [0.012937281498156291, 0.98706271850184368, 0.0], "type": "rv", "id": "[rigidness] held_dp_for"}, {"subtype": "verb_sim", "type": "fac", "id": "verb_sim5"}, {"attr": "rigidness", "rvname": "showed_dp_at", "subtype": "frame", "weights": [6.0016470737574215e-05, 0.99993998352926239, 0.0], "type": "rv", "id": "[rigidness] showed_dp_at"}, {"subtype": "verb_sim", "type": "fac", "id": "verb_sim6"}, {"attr": "rigidness", "rvname": "gave_dp_at", "subtype": "frame", "weights": [2.0407864148562267e-05, 0.99997959213585141, 0.0], "type": "rv", "id": "[rigidness] gave_dp_at"}, {"subtype": "verb_sim", "type": "fac", "id": "verb_sim7"}, {"attr": "rigidness", "rvname": "gave_dp_for", "subtype": "frame", "weights": [6.9945155265709735e-05, 0.99993005484473418, 0.0], "type": "rv", "id": "[rigidness] gave_dp_for"}, {"subtype": "verb_sim", "type": "fac", "id": "verb_sim8"}, {"attr": "rigidness", "rvname": "pulled_dp_over", "subtype": "frame", "weights": [2.5561648366814695e-12, 0.99999999999744382, 0.0], "type": "rv", "id": "[rigidness] pulled_dp_over"}, {"subtype": "verb_sim", "type": "fac", "id": "verb_sim9"}, {"attr": "rigidness", "rvname": "pulled_dp_from", "subtype": "frame", "weights": [5.5711526693650497e-11, 0.99999999994428845, 0.0], "type": "rv", "id": "[rigidness] pulled_dp_from"}, {"subtype": "verb_sim", "type": "fac", "id": "verb_sim10"}, {"attr": "rigidness", "rvname": "broke_dp_in", "subtype": "frame", "weights": [2.0628521478165196e-07, 0.9999997937147852, 0.0], "type": "rv", "id": "[rigidness] broke_dp_in"}, {"subtype": "verb_sim", "type": "fac", "id": "verb_sim11"}, {"attr": "rigidness", "rvname": "broke_dp_with", "subtype": "frame", "weights": [6.3728288900027973e-08, 0.99999993627171113, 0.0], "type": "rv", "id": "[rigidness] broke_dp_with"}, {"subtype": "verb_sim", "type": "fac", "id": "verb_sim12"}, {"attr": "rigidness", "rvname": "carried_dp_on", "subtype": "frame", "weights": [0.00014064610061391994, 0.99985935389938596, 0.0], "type": "rv", "id": "[rigidness] carried_dp_on"}, {"subtype": "verb_sim", "type": "fac", "id": "verb_sim13"}, {"attr": "rigidness", "rvname": "carried_dp_into", "subtype": "frame", "weights": [1.6887341570715966e-05, 0.99998311265842932, 0.0], "type": "rv", "id": "[rigidness] carried_dp_into"}, {"subtype": "verb_sim", "type": "fac", "id": "verb_sim14"}, {"attr": "rigidness", "rvname": "ran_dp_over", "subtype": "frame", "weights": [1.1664817116358086e-06, 0.99999883351828833, 0.0], "type": "rv", "id": "[rigidness] ran_dp_over"}, {"subtype": "verb_sim", "type": "fac", "id": "verb_sim15"}, {"attr": "rigidness", "rvname": "ran_dp_into", "subtype": "frame", "weights": [2.455562427567158e-06, 0.99999754443757249, 0.0], "type": "rv", "id": "[rigidness] ran_dp_into"}, {"subtype": "verb_sim", "type": "fac", "id": "verb_sim16"}, {"attr": "rigidness", "rvname": "picked_dp_from", "subtype": "frame", "weights": [2.0286840223046115e-11, 0.99999999997971312, 0.0], "type": "rv", "id": "[rigidness] picked_dp_from"}, {"subtype": "sel_pref", "type": "fac", "id": "sel_pref17"}, {"attr": "rigidness", "rvname": "breath_vs_air", "subtype": "noun", "weights": [0.15122769987572654, 0.83547564598079926, 0.013296654143474281], "type": "rv", "id": "[rigidness] breath_vs_air"}, {"subtype": "sel_pref", "type": "fac", "id": "sel_pref18"}, {"attr": "rigidness", "rvname": "office_vs_seal", "subtype": "noun", "weights": [0.21014440209708904, 0.77583066757951158, 0.014024930323399352], "type": "rv", "id": "[rigidness] office_vs_seal"}, {"subtype": "sel_pref", "type": "fac", "id": "sel_pref19"}, {"attr": "rigidness", "rvname": "office_vs_master", "subtype": "noun", "weights": [0.41941594571614227, 0.51198627953926479, 0.068597774744592999], "type": "rv", "id": "[rigidness] office_vs_master"}, {"subtype": "sel_pref", "type": "fac", "id": "sel_pref20"}, {"attr": "rigidness", "rvname": "daughter_vs_king", "subtype": "noun", "weights": [0.12907616807216976, 0.85902156594277224, 0.01190226598505797], "type": "rv", "id": "[rigidness] daughter_vs_king"}, {"subtype": "sel_pref", "type": "fac", "id": "sel_pref21"}, {"attr": "rigidness", "rvname": "arm_vs_patient", "subtype": "noun", "weights": [0.64040526054617297, 0.30916350941359477, 0.050431230040232151], "type": "rv", "id": "[rigidness] arm_vs_patient"}, {"specific": "rev", "subtype": "sel_pref", "type": "fac", "id": "sel_pref22"}, {"attr": "rigidness", "rvname": "newspaper_vs_piece", "subtype": "noun", "weights": [0.27120313081857872, 0.7245197053322423, 0.0042771638491790505], "type": "rv", "id": "[rigidness] newspaper_vs_piece"}, {"specific": "rev", "subtype": "sel_pref", "type": "fac", "id": "sel_pref23"}, {"attr": "rigidness", "rvname": "father_vs_hand", "subtype": "noun", "weights": [0.0017599685349057124, 0.99823994063181565, 9.083327867759906e-08], "type": "rv", "id": "[rigidness] father_vs_hand"}, {"specific": "rev", "subtype": "sel_pref", "type": "fac", "id": "sel_pref24"}, {"attr": "rigidness", "rvname": "knife_vs_place", "subtype": "noun", "weights": [0.22715933741965816, 0.74755464337839383, 0.025286019201948035], "type": "rv", "id": "[rigidness] knife_vs_place"}, {"specific": "rev", "subtype": "sel_pref", "type": "fac", "id": "sel_pref25"}, {"attr": "rigidness", "rvname": "brother_vs_wife", "subtype": "noun", "weights": [0.12591576417055325, 0.87387084323068898, 0.00021339259875776794], "type": "rv", "id": "[rigidness] brother_vs_wife"}, {"specific": "rev", "subtype": "sel_pref", "type": "fac", "id": "sel_pref26"}, {"attr": "rigidness", "rvname": "teacher_vs_place", "subtype": "noun", "weights": [0.18488869047979992, 0.79935302388439011, 0.015758285635809791], "type": "rv", "id": "[rigidness] teacher_vs_place"}, {"specific": "rev", "subtype": "sel_pref", "type": "fac", "id": "sel_pref27"}, {"attr": "rigidness", "rvname": "servant_vs_hand", "subtype": "noun", "weights": [0.31229048565765566, 0.68177220035197972, 0.0059373139903646458], "type": "rv", "id": "[rigidness] servant_vs_hand"}, {"specific": "rev", "subtype": "sel_pref", "type": "fac", "id": "sel_pref28"}, {"attr": "rigidness", "rvname": "bow_vs_end", "subtype": "noun", "weights": [0.61433975233697846, 0.34335762894831823, 0.042302618714703345], "type": "rv", "id": "[rigidness] bow_vs_end"}, {"specific": "rev", "subtype": "sel_pref", "type": "fac", "id": "sel_pref29"}, {"attr": "rigidness", "rvname": "lady_vs_arm", "subtype": "noun", "weights": [0.35991071044266076, 0.63933363909234597, 0.00075565046499329166], "type": "rv", "id": "[rigidness] lady_vs_arm"}, {"specific": "rev", "subtype": "sel_pref", "type": "fac", "id": "sel_pref30"}, {"attr": "rigidness", "rvname": "lad_vs_hand", "subtype": "noun", "weights": [0.27056646073082619, 0.72538105185675394, 0.0040524874124200127], "type": "rv", "id": "[rigidness] lad_vs_hand"}, {"specific": "rev", "subtype": "sel_pref", "type": "fac", "id": "sel_pref31"}, {"attr": "rigidness", "rvname": "house_vs_direction", "subtype": "noun", "weights": [0.86204849462537436, 0.098375663947626382, 0.039575841426999318], "type": "rv", "id": "[rigidness] house_vs_direction"}], "stats": {"rvs": {"frame": 16, "noun": 15}, "facs": {"sel_pref": 15, "seed": 2, "verb_sim": 15}, "n_facs": 32, "focus": "took_dp_of", "n_rvs": 31}, "links": [{"source": "seed0", "type": "seed", "target": "[rigidness] took_dp_of", "weights": [0.259935827422, 0.74006417257799995, 0.0]}, {"source": "seed1", "type": "seed", "target": "[rigidness] took_dp_of", "weights": [0.22222222222222227, 0.77777777777777779, 0.0]}, {"source": "verb_sim2", "type": "verb_sim", "target": "[rigidness] took_dp_of", "weights": [0.22222516389049027, 0.7777748361095097, 0.0]}, {"source": "verb_sim2", "type": "verb_sim", "target": "[rigidness] made_dp_in", "weights": [0.22223220708446761, 0.77776779291553244, 0.0]}, {"source": "verb_sim3", "type": "verb_sim", "target": "[rigidness] took_dp_of", "weights": [0.22222233367063318, 0.77777766632936685, 0.0]}, {"source": "verb_sim3", "type": "verb_sim", "target": "[rigidness] made_dp_on", "weights": [0.22223220724795825, 0.77776779275204178, 0.0]}, {"source": "verb_sim4", "type": "verb_sim", "target": "[rigidness] took_dp_of", "weights": [0.24658872041083138, 0.75341127958916854, 0.0]}, {"source": "verb_sim4", "type": "verb_sim", "target": "[rigidness] held_dp_for", "weights": [0.22223093871252048, 0.77776906128747947, 0.0]}, {"source": "verb_sim5", "type": "verb_sim", "target": "[rigidness] took_dp_of", "weights": [0.22233889694246378, 0.77766110305753622, 0.0]}, {"source": "verb_sim5", "type": "verb_sim", "target": "[rigidness] showed_dp_at", "weights": [0.22223220051769904, 0.77776779948230101, 0.0]}, {"source": "verb_sim6", "type": "verb_sim", "target": "[rigidness] took_dp_of", "weights": [0.22226189302755686, 0.77773810697244317, 0.0]}, {"source": "verb_sim6", "type": "verb_sim", "target": "[rigidness] gave_dp_at", "weights": [0.22223220496347393, 0.77776779503652604, 0.0]}, {"source": "verb_sim7", "type": "verb_sim", "target": "[rigidness] took_dp_of", "weights": [0.22235817163762769, 0.77764182836237228, 0.0]}, {"source": "verb_sim7", "type": "verb_sim", "target": "[rigidness] gave_dp_for", "weights": [0.22223219940694391, 0.77776780059305606, 0.0]}, {"source": "verb_sim8", "type": "verb_sim", "target": "[rigidness] took_dp_of", "weights": [0.22222222222719223, 0.77777777777280777, 0.0]}, {"source": "verb_sim8", "type": "verb_sim", "target": "[rigidness] pulled_dp_over", "weights": [0.22223220725439607, 0.77776779274560393, 0.0]}, {"source": "verb_sim9", "type": "verb_sim", "target": "[rigidness] took_dp_of", "weights": [0.22222222233054376, 0.77777777766945622, 0.0]}, {"source": "verb_sim9", "type": "verb_sim", "target": "[rigidness] pulled_dp_from", "weights": [0.22223220725439008, 0.77776779274560992, 0.0]}, {"source": "verb_sim10", "type": "verb_sim", "target": "[rigidness] took_dp_of", "weights": [0.22222262330912315, 0.77777737669087688, 0.0]}, {"source": "verb_sim10", "type": "verb_sim", "target": "[rigidness] broke_dp_in", "weights": [0.22223220723122583, 0.77776779276877417, 0.0]}, {"source": "verb_sim11", "type": "verb_sim", "target": "[rigidness] took_dp_of", "weights": [0.2222223461312518, 0.7777776538687482, 0.0]}, {"source": "verb_sim11", "type": "verb_sim", "target": "[rigidness] broke_dp_with", "weights": [0.22223220724723816, 0.77776779275276176, 0.0]}, {"source": "verb_sim12", "type": "verb_sim", "target": "[rigidness] took_dp_of", "weights": [0.22249558971601618, 0.77750441028398376, 0.0]}, {"source": "verb_sim12", "type": "verb_sim", "target": "[rigidness] carried_dp_on", "weights": [0.22223219148152379, 0.77776780851847616, 0.0]}, {"source": "verb_sim13", "type": "verb_sim", "target": "[rigidness] took_dp_of", "weights": [0.2222550554375077, 0.77774494456249232, 0.0]}, {"source": "verb_sim13", "type": "verb_sim", "target": "[rigidness] carried_dp_into", "weights": [0.22223220535791799, 0.77776779464208201, 0.0]}, {"source": "verb_sim14", "type": "verb_sim", "target": "[rigidness] took_dp_of", "weights": [0.22222448972436742, 0.77777551027563263, 0.0]}, {"source": "verb_sim14", "type": "verb_sim", "target": "[rigidness] ran_dp_over", "weights": [0.22223220712346253, 0.77776779287653752, 0.0]}, {"source": "verb_sim15", "type": "verb_sim", "target": "[rigidness] took_dp_of", "weights": [0.22222699662547205, 0.77777300337452804, 0.0]}, {"source": "verb_sim15", "type": "verb_sim", "target": "[rigidness] ran_dp_into", "weights": [0.22223220697858712, 0.77776779302141286, 0.0]}, {"source": "verb_sim16", "type": "verb_sim", "target": "[rigidness] took_dp_of", "weights": [0.22222222226166649, 0.77777777773833356, 0.0]}, {"source": "verb_sim16", "type": "verb_sim", "target": "[rigidness] picked_dp_from", "weights": [0.22223220725439402, 0.77776779274560592, 0.0]}, {"source": "sel_pref17", "type": "sel_pref", "target": "[rigidness] took_dp_of", "weights": [0.43863750563664239, 0.56136249436335761, 0.0]}, {"source": "sel_pref17", "type": "sel_pref", "target": "[rigidness] breath_vs_air", "weights": [0.20000328571032022, 0.6999967142896798, 0.10000000000000001]}, {"source": "sel_pref18", "type": "sel_pref", "target": "[rigidness] took_dp_of", "weights": [0.49269151285566049, 0.50730848714433951, 0.0]}, {"source": "sel_pref18", "type": "sel_pref", "target": "[rigidness] office_vs_seal", "weights": [0.20000264378715746, 0.69999735621284254, 0.10000000000000001]}, {"source": "sel_pref19", "type": "sel_pref", "target": "[rigidness] took_dp_of", "weights": [0.62725881230953495, 0.3727411876904651, 0.0]}, {"source": "sel_pref19", "type": "sel_pref", "target": "[rigidness] office_vs_master", "weights": [0.2000015257745491, 0.69999847422545081, 0.099999999999999978]}, {"source": "sel_pref20", "type": "sel_pref", "target": "[rigidness] took_dp_of", "weights": [0.41492904224560934, 0.58507095775439066, 0.0]}, {"source": "sel_pref20", "type": "sel_pref", "target": "[rigidness] daughter_vs_king", "weights": [0.20000361968909899, 0.69999638031090106, 0.10000000000000001]}, {"source": "sel_pref21", "type": "sel_pref", "target": "[rigidness] took_dp_of", "weights": [0.70415894308340055, 0.29584105691659945, 0.0]}, {"source": "sel_pref21", "type": "sel_pref", "target": "[rigidness] arm_vs_patient", "weights": [0.20000107872824241, 0.69999892127175767, 0.10000000000000001]}, {"source": "sel_pref22", "type": "sel_pref", "target": "[rigidness] took_dp_of", "weights": [0.72359022277332308, 0.27640977722667698, 0.0]}, {"source": "sel_pref22", "type": "sel_pref", "target": "[rigidness] newspaper_vs_piece", "weights": [0.69999901917804186, 0.20000098082195814, 0.099999999999999992]}, {"source": "sel_pref23", "type": "sel_pref", "target": "[rigidness] took_dp_of", "weights": [0.77749799148049337, 0.22250200851950663, 0.0]}, {"source": "sel_pref23", "type": "sel_pref", "target": "[rigidness] father_vs_hand", "weights": [0.6999992652055087, 0.2000007347944914, 0.10000000000000002]}, {"source": "sel_pref24", "type": "sel_pref", "target": "[rigidness] took_dp_of", "weights": [0.73021289512739607, 0.26978710487260388, 0.0]}, {"source": "sel_pref24", "type": "sel_pref", "target": "[rigidness] knife_vs_place", "weights": [0.69999905135743989, 0.20000094864256013, 0.10000000000000001]}, {"source": "sel_pref25", "type": "sel_pref", "target": "[rigidness] took_dp_of", "weights": [0.75578567303655519, 0.24421432696344481, 0.0]}, {"source": "sel_pref25", "type": "sel_pref", "target": "[rigidness] brother_vs_wife", "weights": [0.69999917035116532, 0.20000082964883473, 0.10000000000000002]}, {"source": "sel_pref26", "type": "sel_pref", "target": "[rigidness] took_dp_of", "weights": [0.74135587545700665, 0.25864412454299335, 0.0]}, {"source": "sel_pref26", "type": "sel_pref", "target": "[rigidness] teacher_vs_place", "weights": [0.69999910420867784, 0.20000089579132216, 0.10000000000000003]}, {"source": "sel_pref27", "type": "sel_pref", "target": "[rigidness] took_dp_of", "weights": [0.7127560386655607, 0.28724396133443925, 0.0]}, {"source": "sel_pref27", "type": "sel_pref", "target": "[rigidness] servant_vs_hand", "weights": [0.69999896523711691, 0.20000103476288308, 0.10000000000000003]}, {"source": "sel_pref28", "type": "sel_pref", "target": "[rigidness] took_dp_of", "weights": [0.58670371350657424, 0.41329628649342581, 0.0]}, {"source": "sel_pref28", "type": "sel_pref", "target": "[rigidness] bow_vs_end", "weights": [0.69999819127377982, 0.2000018087262202, 0.10000000000000001]}, {"source": "sel_pref29", "type": "sel_pref", "target": "[rigidness] took_dp_of", "weights": [0.70071095117130566, 0.29928904882869439, 0.0]}, {"source": "sel_pref29", "type": "sel_pref", "target": "[rigidness] lady_vs_arm", "weights": [0.6999989033330164, 0.20000109666698362, 0.10000000000000001]}, {"source": "sel_pref30", "type": "sel_pref", "target": "[rigidness] took_dp_of", "weights": [0.72377109805020301, 0.27622890194979705, 0.0]}, {"source": "sel_pref30", "type": "sel_pref", "target": "[rigidness] lad_vs_hand", "weights": [0.69999902005969072, 0.20000097994030927, 0.10000000000000001]}, {"source": "sel_pref31", "type": "sel_pref", "target": "[rigidness] took_dp_of", "weights": [0.38657184498959213, 0.61342815501040793, 0.0]}, {"source": "sel_pref31", "type": "sel_pref", "target": "[rigidness] house_vs_direction", "weights": [0.69999592561855295, 0.20000407438144707, 0.10000000000000002]}]}
