{"nodes": [{"attr": "rigidness", "rvname": "drew_dp_on", "focus": true, "subtype": "frame", "weights": [0.014247734734515405, 0.98575226526548454, 0.0], "type": "rv", "id": "[rigidness] drew_dp_on"}, {"specific": "emb", "subtype": "seed", "type": "fac", "id": "seed0", "weights": [0.28693699464, 0.71306300536, 0.0]}, {"subtype": "verb_sim", "type": "fac", "id": "verb_sim1"}, {"attr": "rigidness", "rvname": "gave_dp_at", "subtype": "frame", "weights": [2.0407864148562267e-05, 0.99997959213585141, 0.0], "type": "rv", "id": "[rigidness] gave_dp_at"}, {"subtype": "verb_sim", "type": "fac", "id": "verb_sim2"}, {"attr": "rigidness", "rvname": "gave_dp_for", "subtype": "frame", "weights": [6.9945155265709735e-05, 0.99993005484473418, 0.0], "type": "rv", "id": "[rigidness] gave_dp_for"}, {"subtype": "sel_pref", "type": "fac", "id": "sel_pref3"}, {"attr": "rigidness", "rvname": "cross_vs_door", "subtype": "noun", "weights": [0.05224263689811208, 0.94614265895979677, 0.0016147041420911637], "type": "rv", "id": "[rigidness] cross_vs_door"}], "stats": {"rvs": {"frame": 3, "noun": 1}, "facs": {"sel_pref": 1, "seed": 1, "verb_sim": 2}, "n_facs": 4, "focus": "drew_dp_on", "n_rvs": 4}, "links": [{"source": "seed0", "type": "seed", "target": "[rigidness] drew_dp_on", "weights": [0.28693699464, 0.71306300536, 0.0]}, {"source": "verb_sim1", "type": "verb_sim", "target": "[rigidness] gave_dp_at", "weights": [0.24896829828680467, 0.75103170171319533, 0.0]}, {"source": "verb_sim1", "type": "verb_sim", "target": "[rigidness] drew_dp_on", "weights": [0.22225641592620862, 0.77774358407379129, 0.0]}, {"source": "verb_sim2", "type": "verb_sim", "target": "[rigidness] gave_dp_for", "weights": [0.24895608122945984, 0.75104391877054022, 0.0]}, {"source": "verb_sim2", "type": "verb_sim", "target": "[rigidness] drew_dp_on", "weights": [0.22233941240529817, 0.77766058759470191, 0.0]}, {"source": "sel_pref3", "type": "sel_pref", "target": "[rigidness] drew_dp_on", "weights": [0.30537113797011917, 0.69462886202988083, 0.0]}, {"source": "sel_pref3", "type": "sel_pref", "target": "[rigidness] cross_vs_door", "weights": [0.21591563100396541, 0.68408436899603464, 0.10000000000000002]}]}
