{"nodes": [{"attr": "rigidness", "rvname": "died_op_at", "focus": true, "subtype": "frame", "weights": [9.8653622268337206e-05, 0.99990134637773165, 0.0], "type": "rv", "id": "[rigidness] died_op_at"}, {"specific": "emb", "subtype": "seed", "type": "fac", "id": "seed0", "weights": [0.36125632439800004, 0.63874367560199996, 0.0]}, {"subtype": "verb_sim", "type": "fac", "id": "verb_sim1"}, {"attr": "rigidness", "rvname": "took_op_out", "subtype": "frame", "weights": [3.4839791199674025e-09, 0.99999999651602101, 0.0], "type": "rv", "id": "[rigidness] took_op_out"}, {"subtype": "verb_sim", "type": "fac", "id": "verb_sim2"}, {"attr": "rigidness", "rvname": "lived_op_in", "subtype": "frame", "weights": [1.2764397438324322e-08, 0.99999998723560246, 0.0], "type": "rv", "id": "[rigidness] lived_op_in"}, {"subtype": "verb_sim", "type": "fac", "id": "verb_sim3"}, {"attr": "rigidness", "rvname": "lived_op_at", "subtype": "frame", "weights": [3.7238519933325437e-06, 0.99999627614800668, 0.0], "type": "rv", "id": "[rigidness] lived_op_at"}, {"subtype": "sel_pref", "type": "fac", "id": "sel_pref4"}, {"attr": "rigidness", "rvname": "father_vs_sea", "subtype": "noun", "weights": [0.010377791316366278, 0.98934380865484461, 0.00027840002878913903], "type": "rv", "id": "[rigidness] father_vs_sea"}, {"subtype": "sel_pref", "type": "fac", "id": "sel_pref5"}, {"attr": "rigidness", "rvname": "lady_vs_house", "subtype": "noun", "weights": [0.00019959952753204399, 0.99978717927076444, 1.3221201703542782e-05], "type": "rv", "id": "[rigidness] lady_vs_house"}, {"subtype": "sel_pref", "type": "fac", "id": "sel_pref6"}, {"attr": "rigidness", "rvname": "daughter_vs_place", "subtype": "noun", "weights": [2.6379333216446646e-05, 0.99997359106529338, 2.960149000231946e-08], "type": "rv", "id": "[rigidness] daughter_vs_place"}, {"specific": "rev", "subtype": "sel_pref", "type": "fac", "id": "sel_pref7"}, {"attr": "rigidness", "rvname": "place_vs_wife", "subtype": "noun", "weights": [0.99982907983598579, 0.00016098760345775506, 9.9325605564374756e-06], "type": "rv", "id": "[rigidness] place_vs_wife"}, {"subtype": "noun_sim", "type": "fac", "id": "noun_sim7"}], "stats": {"rvs": {"frame": 4, "noun": 4}, "facs": {"sel_pref": 4, "seed": 1, "noun_sim": 1, "verb_sim": 3}, "n_facs": 9, "focus": "died_op_at", "n_rvs": 8}, "links": [{"source": "seed0", "type": "seed", "target": "[rigidness] died_op_at", "weights": [0.36125632439800004, 0.63874367560199996, 0.0]}, {"source": "verb_sim1", "type": "verb_sim", "target": "[rigidness] took_op_out", "weights": [0.22241401086914697, 0.77758598913085297, 0.0]}, {"source": "verb_sim1", "type": "verb_sim", "target": "[rigidness] died_op_at", "weights": [0.22222222894432861, 0.77777777105567136, 0.0]}, {"source": "verb_sim2", "type": "verb_sim", "target": "[rigidness] lived_op_in", "weights": [0.22241401084873194, 0.77758598915126809, 0.0]}, {"source": "verb_sim2", "type": "verb_sim", "target": "[rigidness] died_op_at", "weights": [0.22222224714095154, 0.77777775285904849, 0.0]}, {"source": "verb_sim3", "type": "verb_sim", "target": "[rigidness] lived_op_at", "weights": [0.22241400282107252, 0.77758599717892751, 0.0]}, {"source": "verb_sim3", "type": "verb_sim", "target": "[rigidness] died_op_at", "weights": [0.22222942388202771, 0.77777057611797229, 0.0]}, {"source": "sel_pref4", "type": "sel_pref", "target": "[rigidness] died_op_at", "weights": [0.24198630584740549, 0.75801369415259445, 0.0]}, {"source": "sel_pref4", "type": "sel_pref", "target": "[rigidness] father_vs_sea", "weights": [0.20015448964621965, 0.6998455103537804, 0.10000000000000001]}, {"source": "sel_pref5", "type": "sel_pref", "target": "[rigidness] died_op_at", "weights": [0.22262798091696523, 0.77737201908303477, 0.0]}, {"source": "sel_pref5", "type": "sel_pref", "target": "[rigidness] lady_vs_house", "weights": [0.20017219699623659, 0.69982780300376346, 0.10000000000000001]}, {"source": "sel_pref6", "type": "sel_pref", "target": "[rigidness] died_op_at", "weights": [0.22227347222095645, 0.7777265277790435, 0.0]}, {"source": "sel_pref6", "type": "sel_pref", "target": "[rigidness] daughter_vs_place", "weights": [0.20017255865036379, 0.69982744134963626, 0.10000000000000001]}, {"source": "sel_pref7", "type": "sel_pref", "target": "[rigidness] died_op_at", "weights": [0.22253906898876569, 0.77746093101123426, 0.0]}, {"source": "sel_pref7", "type": "sel_pref", "target": "[rigidness] place_vs_wife", "weights": [0.6998277060773278, 0.20017229392267225, 0.10000000000000001]}, {"source": "noun_sim7", "type": "noun_sim", "target": "[rigidness] daughter_vs_place", "weights": [0.1907395751655791, 0.66636546326967006, 0.14289496156475073]}, {"source": "noun_sim7", "type": "noun_sim", "target": "[rigidness] place_vs_wife", "weights": [0.69995384400325134, 0.20004607317583978, 0.10000008282090889]}]}
