{"nodes": [{"attr": "size", "rvname": "sat_d", "focus": true, "subtype": "frame", "weights": [0.8861709235894506, 0.11382907641054944, 0.0], "type": "rv", "id": "[size] sat_d"}, {"specific": "emb", "subtype": "seed", "type": "fac", "id": "seed0", "weights": [0.69125930078700004, 0.30874069921300001, 0.0]}, {"subtype": "verb_sim", "type": "fac", "id": "verb_sim1"}, {"attr": "size", "rvname": "walked_d", "subtype": "frame", "weights": [0.99867025043064517, 0.0013297495693547494, 0.0], "type": "rv", "id": "[size] walked_d"}], "stats": {"rvs": {"frame": 2}, "facs": {"seed": 1, "verb_sim": 1}, "n_facs": 2, "focus": "sat_d", "n_rvs": 2}, "links": [{"source": "seed0", "type": "seed", "target": "[size] sat_d", "weights": [0.69125930078700004, 0.30874069921300001, 0.0]}, {"source": "verb_sim1", "type": "verb_sim", "target": "[size] walked_d", "weights": [0.60625516710388883, 0.39374483289611117, 0.0]}, {"source": "verb_sim1", "type": "verb_sim", "target": "[size] sat_d", "weights": [0.77664112880688319, 0.22335887119311681, 0.0]}]}
