{"nodes": [{"attr": "size", "rvname": "hiked_p_up", "focus": true, "subtype": "frame", "weights": [0.18534560082712448, 0.81465439917287552, 0.0], "type": "rv", "id": "[size] hiked_p_up"}, {"specific": "emb", "subtype": "seed", "type": "fac", "id": "seed0", "weights": [0.68158664417699988, 0.31841335582300001, 0.0]}, {"subtype": "sel_pref", "type": "fac", "id": "sel_pref1"}, {"attr": "size", "rvname": "PERSON_vs_hill", "subtype": "noun", "weights": [0.035116293146749356, 0.96484351752604214, 4.0189327208635293e-05], "type": "rv", "id": "[size] PERSON_vs_hill"}, {"subtype": "sel_pref", "type": "fac", "id": "sel_pref2"}, {"attr": "size", "rvname": "PERSON_vs_mountain", "subtype": "noun", "weights": [0.035040291755505569, 0.96462137743731413, 0.00033833080718022394], "type": "rv", "id": "[size] PERSON_vs_mountain"}, {"subtype": "noun_sim", "type": "fac", "id": "noun_sim2"}], "stats": {"rvs": {"frame": 1, "noun": 2}, "facs": {"sel_pref": 2, "seed": 1, "noun_sim": 1}, "n_facs": 4, "focus": "hiked_p_up", "n_rvs": 3}, "links": [{"source": "seed0", "type": "seed", "target": "[size] hiked_p_up", "weights": [0.68158664417699999, 0.31841335582300001, 0.0]}, {"source": "sel_pref1", "type": "sel_pref", "target": "[size] hiked_p_up", "weights": [0.24584071917874595, 0.75415928082125405, 0.0]}, {"source": "sel_pref1", "type": "sel_pref", "target": "[size] PERSON_vs_hill", "weights": [0.40552558051711823, 0.49447441948288184, 0.10000000000000002]}, {"source": "sel_pref2", "type": "sel_pref", "target": "[size] hiked_p_up", "weights": [0.24588238931551396, 0.75411761068448602, 0.0]}, {"source": "sel_pref2", "type": "sel_pref", "target": "[size] PERSON_vs_mountain", "weights": [0.40549838540091404, 0.49450161459908593, 0.10000000000000002]}, {"source": "noun_sim2", "type": "noun_sim", "target": "[size] PERSON_vs_hill", "weights": [0.23252498537939736, 0.62348095006482052, 0.14399406455578204]}, {"source": "noun_sim2", "type": "noun_sim", "target": "[size] PERSON_vs_mountain", "weights": [0.24444103400405592, 0.65546038972929166, 0.10009857626665232]}]}
