{"nodes": [{"attr": "hardness", "rvname": "cut_p_down", "focus": true, "subtype": "frame", "weights": [0.98702446725461712, 0.012975532745382852, 0.0], "type": "rv", "id": "[hardness] cut_p_down"}, {"specific": "emb", "subtype": "seed", "type": "fac", "id": "seed0", "weights": [0.643230055124, 0.356769944876, 0.0]}, {"subtype": "verb_sim", "type": "fac", "id": "verb_sim1"}, {"attr": "hardness", "rvname": "trimmed_p_with", "subtype": "frame", "weights": [0.99870641205381838, 0.0012935879461816494, 0.0], "type": "rv", "id": "[hardness] trimmed_p_with"}, {"subtype": "verb_sim", "type": "fac", "id": "verb_sim2"}, {"attr": "hardness", "rvname": "made_p_for", "subtype": "frame", "weights": [0.99999998711191329, 1.2888086673831149e-08, 0.0], "type": "rv", "id": "[hardness] made_p_for"}, {"subtype": "sel_pref", "type": "fac", "id": "sel_pref3"}, {"attr": "hardness", "rvname": "PERSON_vs_throat", "subtype": "noun", "weights": [0.99964711297760633, 0.00034878391386444589, 4.1031085290525648e-06], "type": "rv", "id": "[hardness] PERSON_vs_throat"}], "stats": {"rvs": {"frame": 3, "noun": 1}, "facs": {"sel_pref": 1, "seed": 1, "verb_sim": 2}, "n_facs": 4, "focus": "cut_p_down", "n_rvs": 4}, "links": [{"source": "seed0", "type": "seed", "target": "[hardness] cut_p_down", "weights": [0.643230055124, 0.356769944876, 0.0]}, {"source": "verb_sim1", "type": "verb_sim", "target": "[hardness] trimmed_p_with", "weights": [0.75363392879857571, 0.24636607120142429, 0.0]}, {"source": "verb_sim1", "type": "verb_sim", "target": "[hardness] cut_p_down", "weights": [0.77558523641791166, 0.22441476358208837, 0.0]}, {"source": "verb_sim2", "type": "verb_sim", "target": "[hardness] made_p_for", "weights": [0.7533403014546769, 0.24665969854532302, 0.0]}, {"source": "verb_sim2", "type": "verb_sim", "target": "[hardness] cut_p_down", "weights": [0.77777775590978426, 0.22222224409021576, 0.0]}, {"source": "sel_pref3", "type": "sel_pref", "target": "[hardness] cut_p_down", "weights": [0.77718442940066224, 0.22281557059933776, 0.0]}, {"source": "sel_pref3", "type": "sel_pref", "target": "[hardness] PERSON_vs_throat", "weights": [0.67807826933039761, 0.22192173066960241, 0.10000000000000002]}]}
