{"nodes": [{"attr": "verb-speed", "rvname": "washed_p_out", "focus": true, "subtype": "frame", "weights": [0.93489066785459585, 0.065109332145404181, 0.0], "type": "rv", "id": "[verb-speed] washed_p_out"}, {"specific": "emb", "subtype": "seed", "type": "fac", "id": "seed0", "weights": [0.8040179830769999, 0.19598201692299999, 0.0]}, {"specific": "hard", "subtype": "seed", "type": "fac", "id": "seed1", "weights": [0.69999999999999996, 0.20000000000000001, 0.10000000000000001]}], "stats": {"rvs": {"frame": 1}, "facs": {"seed": 2}, "n_facs": 2, "focus": "washed_p_out", "n_rvs": 1}, "links": [{"source": "seed0", "type": "seed", "target": "[verb-speed] washed_p_out", "weights": [0.80401798307700001, 0.19598201692300002, 0.0]}, {"source": "seed1", "type": "seed", "target": "[verb-speed] washed_p_out", "weights": [0.77777777777777768, 0.22222222222222227, 0.0]}]}
