{"nodes": [{"attr": "weight", "rvname": "gave_dp_at", "focus": true, "subtype": "frame", "weights": [7.3828773126023353e-09, 0.99999999261712269, 0.0], "type": "rv", "id": "[weight] gave_dp_at"}, {"specific": "emb", "subtype": "seed", "type": "fac", "id": "seed0", "weights": [0.42473569210900003, 0.57526430789100003, 0.0]}, {"subtype": "verb_sim", "type": "fac", "id": "verb_sim1"}, {"attr": "weight", "rvname": "took_dp_from", "subtype": "frame", "weights": [1.7123625284051399e-09, 0.99999999828763753, 0.0], "type": "rv", "id": "[weight] took_dp_from"}, {"subtype": "verb_sim", "type": "fac", "id": "verb_sim2"}, {"attr": "weight", "rvname": "took_dp_by", "subtype": "frame", "weights": [8.3944456646092421e-05, 0.99991605554335394, 0.0], "type": "rv", "id": "[weight] took_dp_by"}, {"subtype": "verb_sim", "type": "fac", "id": "verb_sim3"}, {"attr": "weight", "rvname": "took_dp_at", "subtype": "frame", "weights": [6.3911447328068223e-11, 0.99999999993608857, 0.0], "type": "rv", "id": "[weight] took_dp_at"}, {"subtype": "verb_sim", "type": "fac", "id": "verb_sim4"}, {"attr": "weight", "rvname": "took_dp_of", "subtype": "frame", "weights": [5.1126803565166292e-12, 0.9999999999948872, 0.0], "type": "rv", "id": "[weight] took_dp_of"}, {"subtype": "verb_sim", "type": "fac", "id": "verb_sim5"}, {"attr": "weight", "rvname": "made_dp_on", "subtype": "frame", "weights": [1.1809041979087834e-10, 0.99999999988190957, 0.0], "type": "rv", "id": "[weight] made_dp_on"}, {"subtype": "verb_sim", "type": "fac", "id": "verb_sim6"}, {"attr": "weight", "rvname": "made_dp_with", "subtype": "frame", "weights": [2.8173003121398746e-12, 0.99999999999718259, 0.0], "type": "rv", "id": "[weight] made_dp_with"}, {"subtype": "verb_sim", "type": "fac", "id": "verb_sim7"}, {"attr": "weight", "rvname": "sent_dp_into", "subtype": "frame", "weights": [2.9510470097150057e-05, 0.99997048952990286, 0.0], "type": "rv", "id": "[weight] sent_dp_into"}, {"subtype": "verb_sim", "type": "fac", "id": "verb_sim8"}, {"attr": "weight", "rvname": "sent_dp_with", "subtype": "frame", "weights": [0.000241410061565907, 0.99975858993843403, 0.0], "type": "rv", "id": "[weight] sent_dp_with"}, {"subtype": "verb_sim", "type": "fac", "id": "verb_sim9"}, {"attr": "weight", "rvname": "sent_dp_for", "subtype": "frame", "weights": [0.00059436273026386021, 0.99940563726973608, 0.0], "type": "rv", "id": "[weight] sent_dp_for"}, {"subtype": "verb_sim", "type": "fac", "id": "verb_sim10"}, {"attr": "weight", "rvname": "showed_dp_in", "subtype": "frame", "weights": [2.1826359550199293e-05, 0.99997817364044983, 0.0], "type": "rv", "id": "[weight] showed_dp_in"}, {"subtype": "verb_sim", "type": "fac", "id": "verb_sim11"}, {"attr": "weight", "rvname": "showed_dp_at", "subtype": "frame", "weights": [2.1595082735561197e-07, 0.99999978404917267, 0.0], "type": "rv", "id": "[weight] showed_dp_at"}, {"subtype": "verb_sim", "type": "fac", "id": "verb_sim12"}, {"attr": "weight", "rvname": "drew_dp_in", "subtype": "frame", "weights": [0.13845562961698529, 0.86154437038301479, 0.0], "type": "rv", "id": "[weight] drew_dp_in"}, {"subtype": "verb_sim", "type": "fac", "id": "verb_sim13"}, {"attr": "weight", "rvname": "drew_dp_on", "subtype": "frame", "weights": [0.083562597251372467, 0.91643740274862751, 0.0], "type": "rv", "id": "[weight] drew_dp_on"}, {"subtype": "verb_sim", "type": "fac", "id": "verb_sim14"}, {"attr": "weight", "rvname": "drew_dp_across", "subtype": "frame", "weights": [0.00069422763259565843, 0.99930577236740437, 0.0], "type": "rv", "id": "[weight] drew_dp_across"}, {"subtype": "verb_sim", "type": "fac", "id": "verb_sim15"}, {"attr": "weight", "rvname": "picked_dp_from", "subtype": "frame", "weights": [1.739487121269819e-11, 0.99999999998260503, 0.0], "type": "rv", "id": "[weight] picked_dp_from"}, {"subtype": "verb_sim", "type": "fac", "id": "verb_sim16"}, {"attr": "weight", "rvname": "won_dp_in", "subtype": "frame", "weights": [0.0002651999253695119, 0.99973480007463056, 0.0], "type": "rv", "id": "[weight] won_dp_in"}], "stats": {"rvs": {"frame": 17}, "facs": {"seed": 1, "verb_sim": 16}, "n_facs": 17, "focus": "gave_dp_at", "n_rvs": 17}, "links": [{"source": "seed0", "type": "seed", "target": "[weight] gave_dp_at", "weights": [0.42473569210900003, 0.57526430789100003, 0.0]}, {"source": "verb_sim1", "type": "verb_sim", "target": "[weight] took_dp_from", "weights": [0.22222223657781648, 0.77777776342218352, 0.0]}, {"source": "verb_sim1", "type": "verb_sim", "target": "[weight] gave_dp_at", "weights": [0.22222222555180984, 0.77777777444819007, 0.0]}, {"source": "verb_sim2", "type": "verb_sim", "target": "[weight] took_dp_by", "weights": [0.22222223656427029, 0.77777776343572969, 0.0]}, {"source": "verb_sim2", "type": "verb_sim", "target": "[weight] gave_dp_at", "weights": [0.22238553560694993, 0.77761446439305004, 0.0]}, {"source": "verb_sim3", "type": "verb_sim", "target": "[weight] took_dp_at", "weights": [0.22222223657781676, 0.77777776342218319, 0.0]}, {"source": "verb_sim3", "type": "verb_sim", "target": "[weight] gave_dp_at", "weights": [0.22222222234637035, 0.77777777765362954, 0.0]}, {"source": "verb_sim4", "type": "verb_sim", "target": "[weight] took_dp_of", "weights": [0.22222223657781676, 0.77777776342218319, 0.0]}, {"source": "verb_sim4", "type": "verb_sim", "target": "[weight] gave_dp_at", "weights": [0.22222222223216537, 0.77777777776783463, 0.0]}, {"source": "verb_sim5", "type": "verb_sim", "target": "[weight] made_dp_on", "weights": [0.22222223657781676, 0.7777777634221833, 0.0]}, {"source": "verb_sim5", "type": "verb_sim", "target": "[weight] gave_dp_at", "weights": [0.22222222245158005, 0.77777777754841992, 0.0]}, {"source": "verb_sim6", "type": "verb_sim", "target": "[weight] made_dp_with", "weights": [0.22222223657781676, 0.77777776342218319, 0.0]}, {"source": "verb_sim6", "type": "verb_sim", "target": "[weight] gave_dp_at", "weights": [0.22222222222769369, 0.77777777777230639, 0.0]}, {"source": "verb_sim7", "type": "verb_sim", "target": "[weight] sent_dp_into", "weights": [0.22222223657305212, 0.77777776342694793, 0.0]}, {"source": "verb_sim7", "type": "verb_sim", "target": "[weight] gave_dp_at", "weights": [0.22227960196003901, 0.77772039803996096, 0.0]}, {"source": "verb_sim8", "type": "verb_sim", "target": "[weight] sent_dp_with", "weights": [0.2222222365389287, 0.7777777634610713, 0.0]}, {"source": "verb_sim8", "type": "verb_sim", "target": "[weight] gave_dp_at", "weights": [0.22269137290499655, 0.77730862709500348, 0.0]}, {"source": "verb_sim9", "type": "verb_sim", "target": "[weight] sent_dp_for", "weights": [0.22222223648246447, 0.77777776351753558, 0.0]}, {"source": "verb_sim9", "type": "verb_sim", "target": "[weight] gave_dp_at", "weights": [0.22337621293927648, 0.77662378706072355, 0.0]}, {"source": "verb_sim10", "type": "verb_sim", "target": "[weight] showed_dp_in", "weights": [0.22222223657430154, 0.77777776342569838, 0.0]}, {"source": "verb_sim10", "type": "verb_sim", "target": "[weight] gave_dp_at", "weights": [0.22226460745858972, 0.77773539254141033, 0.0]}, {"source": "verb_sim11", "type": "verb_sim", "target": "[weight] showed_dp_at", "weights": [0.22222223657778195, 0.77777776342221805, 0.0]}, {"source": "verb_sim11", "type": "verb_sim", "target": "[weight] gave_dp_at", "weights": [0.22222264162101701, 0.77777735837898299, 0.0]}, {"source": "verb_sim12", "type": "verb_sim", "target": "[weight] gave_dp_at", "weights": [0.42221587772070984, 0.57778412227929021, 0.0]}, {"source": "verb_sim12", "type": "verb_sim", "target": "[weight] drew_dp_in", "weights": [0.22222222783508197, 0.77777777216491795, 0.0]}, {"source": "verb_sim13", "type": "verb_sim", "target": "[weight] gave_dp_at", "weights": [0.35662701362820337, 0.64337298637179663, 0.0]}, {"source": "verb_sim13", "type": "verb_sim", "target": "[weight] drew_dp_on", "weights": [0.22222222962171118, 0.77777777037828888, 0.0]}, {"source": "verb_sim14", "type": "verb_sim", "target": "[weight] gave_dp_at", "weights": [0.22356978479850112, 0.7764302152014988, 0.0]}, {"source": "verb_sim14", "type": "verb_sim", "target": "[weight] drew_dp_across", "weights": [0.22222223646656425, 0.77777776353343575, 0.0]}, {"source": "verb_sim15", "type": "verb_sim", "target": "[weight] gave_dp_at", "weights": [0.22222222225603167, 0.77777777774396828, 0.0]}, {"source": "verb_sim15", "type": "verb_sim", "target": "[weight] picked_dp_from", "weights": [0.22222223657781676, 0.77777776342218319, 0.0]}, {"source": "verb_sim16", "type": "verb_sim", "target": "[weight] gave_dp_at", "weights": [0.22273749064860199, 0.77726250935139796, 0.0]}, {"source": "verb_sim16", "type": "verb_sim", "target": "[weight] won_dp_in", "weights": [0.22222223653511269, 0.77777776346488725, 0.0]}]}
