{"nodes": [{"attr": "weight", "rvname": "obtained_d", "focus": true, "subtype": "frame", "weights": [0.82799377409795083, 0.17200622590204914, 0.0], "type": "rv", "id": "[weight] obtained_d"}, {"specific": "emb", "subtype": "seed", "type": "fac", "id": "seed0", "weights": [0.65022525824100008, 0.34977474175899997, 0.0]}, {"subtype": "verb_sim", "type": "fac", "id": "verb_sim1"}, {"attr": "weight", "rvname": "received_d", "subtype": "frame", "weights": [0.92539329502727086, 0.074606704972729102, 0.0], "type": "rv", "id": "[weight] received_d"}], "stats": {"rvs": {"frame": 2}, "facs": {"seed": 1, "verb_sim": 1}, "n_facs": 2, "focus": "obtained_d", "n_rvs": 2}, "links": [{"source": "seed0", "type": "seed", "target": "[weight] obtained_d", "weights": [0.65022525824100008, 0.34977474175899997, 0.0]}, {"source": "verb_sim1", "type": "verb_sim", "target": "[weight] received_d", "weights": [0.58345847680055563, 0.41654152319944437, 0.0]}, {"source": "verb_sim1", "type": "verb_sim", "target": "[weight] obtained_d", "weights": [0.7214057788164715, 0.27859422118352845, 0.0]}]}
